README.md
setup.py
leakylan/__init__.py
leakylan/lan.py
leakylan.egg-info/PKG-INFO
leakylan.egg-info/SOURCES.txt
leakylan.egg-info/dependency_links.txt
leakylan.egg-info/entry_points.txt
leakylan.egg-info/top_level.txt