Metadata-Version: 2.1
Name: leakylan
Version: 0.2.3
Summary: Simple File sharing Service over LAN.
Home-page: https://github.com/Anish-M-code/Leaky-LAN
Author: Anish M
Author-email: aneesh25861@gmail.com
License: MIT License
Keywords: File Sharing Service,student project
Platform: UNKNOWN
Classifier: Development Status :: 5 - Production/Stable
Classifier: Intended Audience :: Developers
Classifier: Topic :: Software Development
Classifier: License :: OSI Approved :: MIT License
Classifier: Intended Audience :: Developers
Classifier: Intended Audience :: Education
Classifier: Intended Audience :: End Users/Desktop
Classifier: Topic :: Communications :: File Sharing
